{
  "events": [
    {
      "displayName": "Load - /path1 [ami/pmv]",
      "internalName": "E_LOAD_PATH1_AMIPMV",
      "capturePersonalData": false,
      "active": true,
      "tags": [
        "funnel [ami/pmv]"
      ],
      "trigger": "EveryStep",
      "publish": "Immediate",
      "mode": "Basic",
      "javascript": "// NOTE: Do not change event name\nfunction E_LOAD_PATH1_AMIPMV()\n{\n    if ($P[\"TL.STEP_SCREENVIEW_TYPE\"].firstValue().toUpperCase() == \"LOAD\" && $P[\"TL.STEP_SCREENVIEW_URL\"].firstValue().toUpperCase() == \"URL\" && $P[\"TL.STEP_SCREENVIEW_NAME\"].firstValue().toUpperCase() == \"NAME\")\n    {\n        $F.setFacts(\"E_LOAD_PATH1_AMIPMV\");\n    }\n}",
      "conditionGroup": {
        "conditionOperator": "And",
        "distanceOperator": "GreaterThan",
        "conditions": [
          {
            "leftOperand": {
              "displayName": "Step - ScreenView Type",
              "internalName": "STEP_SCREENVIEW_TYPE",
              "type": "StepAttribute"
            },
            "leftOperandValueType": "Pattern",
            "method": "firstValue()",
            "conditionOperator": "Equal",
            "rightOperandValue": "load",
            "rightOperandValueType": "TextLiteral",
            "caseSensitive": false
          },
          {
            "leftOperand": {
              "displayName": "Step - Screenview URL",
              "internalName": "STEP_SCREENVIEW_URL",
              "type": "StepAttribute"
            },
            "leftOperandValueType": "Pattern",
            "method": "firstValue()",
            "conditionOperator": "Equal",
            "rightOperandValue": "url",
            "rightOperandValueType": "TextLiteral",
            "caseSensitive": false
          },
          {
            "leftOperand": {
              "displayName": "Step - ScreenView Name",
              "internalName": "STEP_SCREENVIEW_NAME",
              "type": "StepAttribute"
            },
            "leftOperandValueType": "Pattern",
            "method": "firstValue()",
            "conditionOperator": "Equal",
            "rightOperandValue": "name",
            "rightOperandValueType": "TextLiteral",
            "caseSensitive": false
          }
        ],
        "lowerBound": 0.0,
        "upperBound": 0.0
      },
      "referenceValueType": "Custom",
      "valueType": "Text",
      "storeMetrics": "Count",
      "track": "AllOccurrence",
      "forSupportUserOnly": false,
      "buildingBlockOnly": false,
      "discardSession": false,
      "geoAnalyticsEnabled": false,
      "dimensionGroups": {}
    },
    {
      "displayName": "Load - /path2 [ami/pmv]",
      "internalName": "E_LOAD_PATH2_AMIPMV",
      "capturePersonalData": false,
      "active": true,
      "tags": [
        "funnel [ami/pmv]"
      ],
      "trigger": "EveryStep",
      "publish": "Immediate",
      "mode": "Basic",
      "javascript": "// NOTE: Do not change event name\nfunction E_LOAD_PATH2_AMIPMV()\n{\n    if ($P[\"TL.STEP_SCREENVIEW_TYPE\"].firstValue().toUpperCase() == \"LOAD\" && $P[\"TL.STEP_SCREENVIEW_URL\"].firstValue().toUpperCase() == \"URL\" && $P[\"TL.STEP_SCREENVIEW_NAME\"].firstValue().toUpperCase() == \"NAME\")\n    {\n        $F.setFacts(\"E_LOAD_PATH2_AMIPMV\");\n    }\n}",
      "conditionGroup": {
        "conditionOperator": "And",
        "distanceOperator": "GreaterThan",
        "conditions": [
          {
            "leftOperand": {
              "displayName": "Step - ScreenView Type",
              "internalName": "STEP_SCREENVIEW_TYPE",
              "type": "StepAttribute"
            },
            "leftOperandValueType": "Pattern",
            "method": "firstValue()",
            "conditionOperator": "Equal",
            "rightOperandValue": "load",
            "rightOperandValueType": "TextLiteral",
            "caseSensitive": false
          },
          {
            "leftOperand": {
              "displayName": "Step - Screenview URL",
              "internalName": "STEP_SCREENVIEW_URL",
              "type": "StepAttribute"
            },
            "leftOperandValueType": "Pattern",
            "method": "firstValue()",
            "conditionOperator": "Equal",
            "rightOperandValue": "url",
            "rightOperandValueType": "TextLiteral",
            "caseSensitive": false
          },
          {
            "leftOperand": {
              "displayName": "Step - ScreenView Name",
              "internalName": "STEP_SCREENVIEW_NAME",
              "type": "StepAttribute"
            },
            "leftOperandValueType": "Pattern",
            "method": "firstValue()",
            "conditionOperator": "Equal",
            "rightOperandValue": "name",
            "rightOperandValueType": "TextLiteral",
            "caseSensitive": false
          }
        ],
        "lowerBound": 0.0,
        "upperBound": 0.0
      },
      "referenceValueType": "Custom",
      "valueType": "Text",
      "storeMetrics": "Count",
      "track": "AllOccurrence",
      "forSupportUserOnly": false,
      "buildingBlockOnly": false,
      "discardSession": false,
      "geoAnalyticsEnabled": false,
      "dimensionGroups": {}
    },
    {
      "displayName": "Load - /path3 [ami/pmv]",
      "internalName": "E_LOAD_PATH3_AMIPMV",
      "capturePersonalData": false,
      "active": true,
      "tags": [
        "funnel [ami/pmv]"
      ],
      "trigger": "EveryStep",
      "publish": "Immediate",
      "mode": "Basic",
      "javascript": "// NOTE: Do not change event name\nfunction E_LOAD_PATH3_AMIPMV()\n{\n    if ($P[\"TL.STEP_SCREENVIEW_TYPE\"].firstValue().toUpperCase() == \"LOAD\" && $P[\"TL.STEP_SCREENVIEW_URL\"].firstValue().toUpperCase() == \"URL\" && $P[\"TL.STEP_SCREENVIEW_NAME\"].firstValue().toUpperCase() == \"NAME\")\n    {\n        $F.setFacts(\"E_LOAD_PATH3_AMIPMV\");\n    }\n}",
      "conditionGroup": {
        "conditionOperator": "And",
        "distanceOperator": "GreaterThan",
        "conditions": [
          {
            "leftOperand": {
              "displayName": "Step - ScreenView Type",
              "internalName": "STEP_SCREENVIEW_TYPE",
              "type": "StepAttribute"
            },
            "leftOperandValueType": "Pattern",
            "method": "firstValue()",
            "conditionOperator": "Equal",
            "rightOperandValue": "load",
            "rightOperandValueType": "TextLiteral",
            "caseSensitive": false
          },
          {
            "leftOperand": {
              "displayName": "Step - Screenview URL",
              "internalName": "STEP_SCREENVIEW_URL",
              "type": "StepAttribute"
            },
            "leftOperandValueType": "Pattern",
            "method": "firstValue()",
            "conditionOperator": "Equal",
            "rightOperandValue": "url",
            "rightOperandValueType": "TextLiteral",
            "caseSensitive": false
          },
          {
            "leftOperand": {
              "displayName": "Step - ScreenView Name",
              "internalName": "STEP_SCREENVIEW_NAME",
              "type": "StepAttribute"
            },
            "leftOperandValueType": "Pattern",
            "method": "firstValue()",
            "conditionOperator": "Equal",
            "rightOperandValue": "name",
            "rightOperandValueType": "TextLiteral",
            "caseSensitive": false
          }
        ],
        "lowerBound": 0.0,
        "upperBound": 0.0
      },
      "referenceValueType": "Custom",
      "valueType": "Text",
      "storeMetrics": "Count",
      "track": "AllOccurrence",
      "forSupportUserOnly": false,
      "buildingBlockOnly": false,
      "discardSession": false,
      "geoAnalyticsEnabled": false,
      "dimensionGroups": {}
    },
    {
      "displayName": "Load - /path4 [ami/pmv]",
      "internalName": "E_LOAD_PATH4_AMIPMV",
      "capturePersonalData": false,
      "active": true,
      "tags": [
        "funnel [ami/pmv]"
      ],
      "trigger": "EveryStep",
      "publish": "Immediate",
      "mode": "Basic",
      "javascript": "// NOTE: Do not change event name\nfunction E_LOAD_PATH4_AMIPMV()\n{\n    if ($P[\"TL.STEP_SCREENVIEW_TYPE\"].firstValue().toUpperCase() == \"LOAD\" && $P[\"TL.STEP_SCREENVIEW_URL\"].firstValue().toUpperCase() == \"URL\" && $P[\"TL.STEP_SCREENVIEW_NAME\"].firstValue().toUpperCase() == \"NAME\")\n    {\n        $F.setFacts(\"E_LOAD_PATH4_AMIPMV\");\n    }\n}",
      "conditionGroup": {
        "conditionOperator": "And",
        "distanceOperator": "GreaterThan",
        "conditions": [
          {
            "leftOperand": {
              "displayName": "Step - ScreenView Type",
              "internalName": "STEP_SCREENVIEW_TYPE",
              "type": "StepAttribute"
            },
            "leftOperandValueType": "Pattern",
            "method": "firstValue()",
            "conditionOperator": "Equal",
            "rightOperandValue": "load",
            "rightOperandValueType": "TextLiteral",
            "caseSensitive": false
          },
          {
            "leftOperand": {
              "displayName": "Step - Screenview URL",
              "internalName": "STEP_SCREENVIEW_URL",
              "type": "StepAttribute"
            },
            "leftOperandValueType": "Pattern",
            "method": "firstValue()",
            "conditionOperator": "Equal",
            "rightOperandValue": "url",
            "rightOperandValueType": "TextLiteral",
            "caseSensitive": false
          },
          {
            "leftOperand": {
              "displayName": "Step - ScreenView Name",
              "internalName": "STEP_SCREENVIEW_NAME",
              "type": "StepAttribute"
            },
            "leftOperandValueType": "Pattern",
            "method": "firstValue()",
            "conditionOperator": "Equal",
            "rightOperandValue": "name",
            "rightOperandValueType": "TextLiteral",
            "caseSensitive": false
          }
        ],
        "lowerBound": 0.0,
        "upperBound": 0.0
      },
      "referenceValueType": "Custom",
      "valueType": "Text",
      "storeMetrics": "Count",
      "track": "AllOccurrence",
      "forSupportUserOnly": false,
      "buildingBlockOnly": false,
      "discardSession": false,
      "geoAnalyticsEnabled": false,
      "dimensionGroups": {}
    },
    {
      "displayName": "Load - /path5 [ami/pmv]",
      "internalName": "E_LOAD_PATH5_AMIPMV",
      "capturePersonalData": false,
      "active": true,
      "tags": [
        "funnel [ami/pmv]"
      ],
      "trigger": "EveryStep",
      "publish": "Immediate",
      "mode": "Basic",
      "javascript": "// NOTE: Do not change event name\nfunction E_LOAD_PATH5_AMIPMV()\n{\n    if ($P[\"TL.STEP_SCREENVIEW_TYPE\"].firstValue().toUpperCase() == \"LOAD\" && $P[\"TL.STEP_SCREENVIEW_URL\"].firstValue().toUpperCase() == \"URL\" && $P[\"TL.STEP_SCREENVIEW_NAME\"].firstValue().toUpperCase() == \"NAME\")\n    {\n        $F.setFacts(\"E_LOAD_PATH5_AMIPMV\");\n    }\n}",
      "conditionGroup": {
        "conditionOperator": "And",
        "distanceOperator": "GreaterThan",
        "conditions": [
          {
            "leftOperand": {
              "displayName": "Step - ScreenView Type",
              "internalName": "STEP_SCREENVIEW_TYPE",
              "type": "StepAttribute"
            },
            "leftOperandValueType": "Pattern",
            "method": "firstValue()",
            "conditionOperator": "Equal",
            "rightOperandValue": "load",
            "rightOperandValueType": "TextLiteral",
            "caseSensitive": false
          },
          {
            "leftOperand": {
              "displayName": "Step - Screenview URL",
              "internalName": "STEP_SCREENVIEW_URL",
              "type": "StepAttribute"
            },
            "leftOperandValueType": "Pattern",
            "method": "firstValue()",
            "conditionOperator": "Equal",
            "rightOperandValue": "url",
            "rightOperandValueType": "TextLiteral",
            "caseSensitive": false
          },
          {
            "leftOperand": {
              "displayName": "Step - ScreenView Name",
              "internalName": "STEP_SCREENVIEW_NAME",
              "type": "StepAttribute"
            },
            "leftOperandValueType": "Pattern",
            "method": "firstValue()",
            "conditionOperator": "Equal",
            "rightOperandValue": "name",
            "rightOperandValueType": "TextLiteral",
            "caseSensitive": false
          }
        ],
        "lowerBound": 0.0,
        "upperBound": 0.0
      },
      "referenceValueType": "Custom",
      "valueType": "Text",
      "storeMetrics": "Count",
      "track": "AllOccurrence",
      "forSupportUserOnly": false,
      "buildingBlockOnly": false,
      "discardSession": false,
      "geoAnalyticsEnabled": false,
      "dimensionGroups": {}
    },
    {
      "displayName": "Load - /path6 [ami/pmv]",
      "internalName": "E_LOAD_PATH6_AMIPMV",
      "capturePersonalData": false,
      "active": true,
      "tags": [
        "funnel [ami/pmv]"
      ],
      "trigger": "EveryStep",
      "publish": "Immediate",
      "mode": "Basic",
      "javascript": "// NOTE: Do not change event name\nfunction E_LOAD_PATH6_AMIPMV()\n{\n    if ($P[\"TL.STEP_SCREENVIEW_TYPE\"].firstValue().toUpperCase() == \"LOAD\" && $P[\"TL.STEP_SCREENVIEW_URL\"].firstValue().toUpperCase() == \"URL\" && $P[\"TL.STEP_SCREENVIEW_NAME\"].firstValue().toUpperCase() == \"NAME\")\n    {\n        $F.setFacts(\"E_LOAD_PATH6_AMIPMV\");\n    }\n}",
      "conditionGroup": {
        "conditionOperator": "And",
        "distanceOperator": "GreaterThan",
        "conditions": [
          {
            "leftOperand": {
              "displayName": "Step - ScreenView Type",
              "internalName": "STEP_SCREENVIEW_TYPE",
              "type": "StepAttribute"
            },
            "leftOperandValueType": "Pattern",
            "method": "firstValue()",
            "conditionOperator": "Equal",
            "rightOperandValue": "load",
            "rightOperandValueType": "TextLiteral",
            "caseSensitive": false
          },
          {
            "leftOperand": {
              "displayName": "Step - Screenview URL",
              "internalName": "STEP_SCREENVIEW_URL",
              "type": "StepAttribute"
            },
            "leftOperandValueType": "Pattern",
            "method": "firstValue()",
            "conditionOperator": "Equal",
            "rightOperandValue": "url",
            "rightOperandValueType": "TextLiteral",
            "caseSensitive": false
          },
          {
            "leftOperand": {
              "displayName": "Step - ScreenView Name",
              "internalName": "STEP_SCREENVIEW_NAME",
              "type": "StepAttribute"
            },
            "leftOperandValueType": "Pattern",
            "method": "firstValue()",
            "conditionOperator": "Equal",
            "rightOperandValue": "name",
            "rightOperandValueType": "TextLiteral",
            "caseSensitive": false
          }
        ],
        "lowerBound": 0.0,
        "upperBound": 0.0
      },
      "referenceValueType": "Custom",
      "valueType": "Text",
      "storeMetrics": "Count",
      "track": "AllOccurrence",
      "forSupportUserOnly": false,
      "buildingBlockOnly": false,
      "discardSession": false,
      "geoAnalyticsEnabled": false,
      "dimensionGroups": {}
    },
    {
      "displayName": "Load - /path7 [ami/pmv]",
      "internalName": "E_LOAD_PATH7_AMIPMV",
      "capturePersonalData": false,
      "active": true,
      "tags": [
        "funnel [ami/pmv]"
      ],
      "trigger": "EveryStep",
      "publish": "Immediate",
      "mode": "Basic",
      "javascript": "// NOTE: Do not change event name\nfunction E_LOAD_PATH7_AMIPMV()\n{\n    if ($P[\"TL.STEP_SCREENVIEW_TYPE\"].firstValue().toUpperCase() == \"LOAD\" && $P[\"TL.STEP_SCREENVIEW_URL\"].firstValue().toUpperCase() == \"URL\" && $P[\"TL.STEP_SCREENVIEW_NAME\"].firstValue().toUpperCase() == \"NAME\")\n    {\n        $F.setFacts(\"E_LOAD_PATH7_AMIPMV\");\n    }\n}",
      "conditionGroup": {
        "conditionOperator": "And",
        "distanceOperator": "GreaterThan",
        "conditions": [
          {
            "leftOperand": {
              "displayName": "Step - ScreenView Type",
              "internalName": "STEP_SCREENVIEW_TYPE",
              "type": "StepAttribute"
            },
            "leftOperandValueType": "Pattern",
            "method": "firstValue()",
            "conditionOperator": "Equal",
            "rightOperandValue": "load",
            "rightOperandValueType": "TextLiteral",
            "caseSensitive": false
          },
          {
            "leftOperand": {
              "displayName": "Step - Screenview URL",
              "internalName": "STEP_SCREENVIEW_URL",
              "type": "StepAttribute"
            },
            "leftOperandValueType": "Pattern",
            "method": "firstValue()",
            "conditionOperator": "Equal",
            "rightOperandValue": "url",
            "rightOperandValueType": "TextLiteral",
            "caseSensitive": false
          },
          {
            "leftOperand": {
              "displayName": "Step - ScreenView Name",
              "internalName": "STEP_SCREENVIEW_NAME",
              "type": "StepAttribute"
            },
            "leftOperandValueType": "Pattern",
            "method": "firstValue()",
            "conditionOperator": "Equal",
            "rightOperandValue": "name",
            "rightOperandValueType": "TextLiteral",
            "caseSensitive": false
          }
        ],
        "lowerBound": 0.0,
        "upperBound": 0.0
      },
      "referenceValueType": "Custom",
      "valueType": "Text",
      "storeMetrics": "Count",
      "track": "AllOccurrence",
      "forSupportUserOnly": false,
      "buildingBlockOnly": false,
      "discardSession": false,
      "geoAnalyticsEnabled": false,
      "dimensionGroups": {}
    },
    {
      "displayName": "Load - /path8 [ami/pmv]",
      "internalName": "E_LOAD_PATH8_AMIPMV",
      "capturePersonalData": false,
      "active": true,
      "tags": [
        "funnel [ami/pmv]"
      ],
      "trigger": "EveryStep",
      "publish": "Immediate",
      "mode": "Basic",
      "javascript": "// NOTE: Do not change event name\nfunction E_LOAD_PATH8_AMIPMV()\n{\n    if ($P[\"TL.STEP_SCREENVIEW_TYPE\"].firstValue().toUpperCase() == \"LOAD\" && $P[\"TL.STEP_SCREENVIEW_URL\"].firstValue().toUpperCase() == \"URL\" && $P[\"TL.STEP_SCREENVIEW_NAME\"].firstValue().toUpperCase() == \"NAME\")\n    {\n        $F.setFacts(\"E_LOAD_PATH8_AMIPMV\");\n    }\n}",
      "conditionGroup": {
        "conditionOperator": "And",
        "distanceOperator": "GreaterThan",
        "conditions": [
          {
            "leftOperand": {
              "displayName": "Step - ScreenView Type",
              "internalName": "STEP_SCREENVIEW_TYPE",
              "type": "StepAttribute"
            },
            "leftOperandValueType": "Pattern",
            "method": "firstValue()",
            "conditionOperator": "Equal",
            "rightOperandValue": "load",
            "rightOperandValueType": "TextLiteral",
            "caseSensitive": false
          },
          {
            "leftOperand": {
              "displayName": "Step - Screenview URL",
              "internalName": "STEP_SCREENVIEW_URL",
              "type": "StepAttribute"
            },
            "leftOperandValueType": "Pattern",
            "method": "firstValue()",
            "conditionOperator": "Equal",
            "rightOperandValue": "url",
            "rightOperandValueType": "TextLiteral",
            "caseSensitive": false
          },
          {
            "leftOperand": {
              "displayName": "Step - ScreenView Name",
              "internalName": "STEP_SCREENVIEW_NAME",
              "type": "StepAttribute"
            },
            "leftOperandValueType": "Pattern",
            "method": "firstValue()",
            "conditionOperator": "Equal",
            "rightOperandValue": "name",
            "rightOperandValueType": "TextLiteral",
            "caseSensitive": false
          }
        ],
        "lowerBound": 0.0,
        "upperBound": 0.0
      },
      "referenceValueType": "Custom",
      "valueType": "Text",
      "storeMetrics": "Count",
      "track": "AllOccurrence",
      "forSupportUserOnly": false,
      "buildingBlockOnly": false,
      "discardSession": false,
      "geoAnalyticsEnabled": false,
      "dimensionGroups": {}
    },
    {
      "displayName": "Load - /path9 [ami/pmv]",
      "internalName": "E_LOAD_PATH9_AMIPMV",
      "capturePersonalData": false,
      "active": true,
      "tags": [
        "funnel [ami/pmv]"
      ],
      "trigger": "EveryStep",
      "publish": "Immediate",
      "mode": "Basic",
      "javascript": "// NOTE: Do not change event name\nfunction E_LOAD_PATH9_AMIPMV()\n{\n    if ($P[\"TL.STEP_SCREENVIEW_TYPE\"].firstValue().toUpperCase() == \"LOAD\" && $P[\"TL.STEP_SCREENVIEW_URL\"].firstValue().toUpperCase() == \"URL\" && $P[\"TL.STEP_SCREENVIEW_NAME\"].firstValue().toUpperCase() == \"NAME\")\n    {\n        $F.setFacts(\"E_LOAD_PATH9_AMIPMV\");\n    }\n}",
      "conditionGroup": {
        "conditionOperator": "And",
        "distanceOperator": "GreaterThan",
        "conditions": [
          {
            "leftOperand": {
              "displayName": "Step - ScreenView Type",
              "internalName": "STEP_SCREENVIEW_TYPE",
              "type": "StepAttribute"
            },
            "leftOperandValueType": "Pattern",
            "method": "firstValue()",
            "conditionOperator": "Equal",
            "rightOperandValue": "load",
            "rightOperandValueType": "TextLiteral",
            "caseSensitive": false
          },
          {
            "leftOperand": {
              "displayName": "Step - Screenview URL",
              "internalName": "STEP_SCREENVIEW_URL",
              "type": "StepAttribute"
            },
            "leftOperandValueType": "Pattern",
            "method": "firstValue()",
            "conditionOperator": "Equal",
            "rightOperandValue": "url",
            "rightOperandValueType": "TextLiteral",
            "caseSensitive": false
          },
          {
            "leftOperand": {
              "displayName": "Step - ScreenView Name",
              "internalName": "STEP_SCREENVIEW_NAME",
              "type": "StepAttribute"
            },
            "leftOperandValueType": "Pattern",
            "method": "firstValue()",
            "conditionOperator": "Equal",
            "rightOperandValue": "name",
            "rightOperandValueType": "TextLiteral",
            "caseSensitive": false
          }
        ],
        "lowerBound": 0.0,
        "upperBound": 0.0
      },
      "referenceValueType": "Custom",
      "valueType": "Text",
      "storeMetrics": "Count",
      "track": "AllOccurrence",
      "forSupportUserOnly": false,
      "buildingBlockOnly": false,
      "discardSession": false,
      "geoAnalyticsEnabled": false,
      "dimensionGroups": {}
    },
    {
      "displayName": "Load - /pathConfirm [ami/pmv]",
      "internalName": "E_LOAD_PATHCONFIRM_AMIPMV",
      "capturePersonalData": false,
      "active": true,
      "tags": [
        "funnel [ami/pmv]"
      ],
      "trigger": "EveryStep",
      "publish": "Immediate",
      "mode": "Basic",
      "javascript": "// NOTE: Do not change event name\nfunction E_LOAD_PATHCONFIRM_AMIPMV()\n{\n    if ($P[\"TL.STEP_SCREENVIEW_TYPE\"].firstValue().toUpperCase() == \"LOAD\" && $P[\"TL.STEP_SCREENVIEW_URL\"].firstValue().toUpperCase() == \"URL\" && $P[\"TL.STEP_SCREENVIEW_NAME\"].firstValue().toUpperCase() == \"NAME\")\n    {\n        $F.setFacts(\"E_LOAD_PATHCONFIRM_AMIPMV\");\n    }\n}",
      "conditionGroup": {
        "conditionOperator": "And",
        "distanceOperator": "GreaterThan",
        "conditions": [
          {
            "leftOperand": {
              "displayName": "Step - ScreenView Type",
              "internalName": "STEP_SCREENVIEW_TYPE",
              "type": "StepAttribute"
            },
            "leftOperandValueType": "Pattern",
            "method": "firstValue()",
            "conditionOperator": "Equal",
            "rightOperandValue": "load",
            "rightOperandValueType": "TextLiteral",
            "caseSensitive": false
          },
          {
            "leftOperand": {
              "displayName": "Step - Screenview URL",
              "internalName": "STEP_SCREENVIEW_URL",
              "type": "StepAttribute"
            },
            "leftOperandValueType": "Pattern",
            "method": "firstValue()",
            "conditionOperator": "Equal",
            "rightOperandValue": "url",
            "rightOperandValueType": "TextLiteral",
            "caseSensitive": false
          },
          {
            "leftOperand": {
              "displayName": "Step - ScreenView Name",
              "internalName": "STEP_SCREENVIEW_NAME",
              "type": "StepAttribute"
            },
            "leftOperandValueType": "Pattern",
            "method": "firstValue()",
            "conditionOperator": "Equal",
            "rightOperandValue": "name",
            "rightOperandValueType": "TextLiteral",
            "caseSensitive": false
          }
        ],
        "lowerBound": 0.0,
        "upperBound": 0.0
      },
      "referenceValueType": "Custom",
      "valueType": "Text",
      "storeMetrics": "Count",
      "track": "AllOccurrence",
      "forSupportUserOnly": false,
      "buildingBlockOnly": false,
      "discardSession": false,
      "geoAnalyticsEnabled": false,
      "dimensionGroups": {}
    },
    {
      "displayName": "Load - /pathRetrieve [ami/pmv]",
      "internalName": "E_LOAD_PATHRETRIEVE_AMIPMV",
      "capturePersonalData": false,
      "active": true,
      "tags": [
        "funnel [ami/pmv]"
      ],
      "trigger": "EveryStep",
      "publish": "Immediate",
      "mode": "Basic",
      "javascript": "// NOTE: Do not change event name\nfunction E_LOAD_PATHRETRIEVE_AMIPMV()\n{\n    if ($P[\"TL.STEP_SCREENVIEW_TYPE\"].firstValue().toUpperCase() == \"LOAD\" && $P[\"TL.STEP_SCREENVIEW_URL\"].firstValue().toUpperCase() == \"URL\" && $P[\"TL.STEP_SCREENVIEW_NAME\"].firstValue().toUpperCase() == \"NAME\")\n    {\n        $F.setFacts(\"E_LOAD_PATHRETRIEVE_AMIPMV\");\n    }\n}",
      "conditionGroup": {
        "conditionOperator": "And",
        "distanceOperator": "GreaterThan",
        "conditions": [
          {
            "leftOperand": {
              "displayName": "Step - ScreenView Type",
              "internalName": "STEP_SCREENVIEW_TYPE",
              "type": "StepAttribute"
            },
            "leftOperandValueType": "Pattern",
            "method": "firstValue()",
            "conditionOperator": "Equal",
            "rightOperandValue": "load",
            "rightOperandValueType": "TextLiteral",
            "caseSensitive": false
          },
          {
            "leftOperand": {
              "displayName": "Step - Screenview URL",
              "internalName": "STEP_SCREENVIEW_URL",
              "type": "StepAttribute"
            },
            "leftOperandValueType": "Pattern",
            "method": "firstValue()",
            "conditionOperator": "Equal",
            "rightOperandValue": "url",
            "rightOperandValueType": "TextLiteral",
            "caseSensitive": false
          },
          {
            "leftOperand": {
              "displayName": "Step - ScreenView Name",
              "internalName": "STEP_SCREENVIEW_NAME",
              "type": "StepAttribute"
            },
            "leftOperandValueType": "Pattern",
            "method": "firstValue()",
            "conditionOperator": "Equal",
            "rightOperandValue": "name",
            "rightOperandValueType": "TextLiteral",
            "caseSensitive": false
          }
        ],
        "lowerBound": 0.0,
        "upperBound": 0.0
      },
      "referenceValueType": "Custom",
      "valueType": "Text",
      "storeMetrics": "Count",
      "track": "AllOccurrence",
      "forSupportUserOnly": false,
      "buildingBlockOnly": false,
      "discardSession": false,
      "geoAnalyticsEnabled": false,
      "dimensionGroups": {}
    },
    {
      "displayName": "Funnel highest [ami/pmv]",
      "internalName": "E_FUNNEL_HIGHEST_AMIPMV",
      "capturePersonalData": false,
      "active": true,
      "tags": [
        "funnel [ami/pmv]"
      ],
      "trigger": "EveryStep",
      "publish": "Immediate",
      "mode": "Advanced",
      "javascript": "// NOTE: Do not change event name\nfunction E_FUNNEL_HIGHEST_AMIPMV()\n{\n    if ($F.getLastHitNumber(\"E_LOAD_PATHCONFIRM_AMIPMV\") == $H.HitNumber && $F.getLastStepNumber(\"E_LOAD_PATHCONFIRM_AMIPMV\") == $H.StepNumber)\n    {\n        $F.setFacts(\"E_FUNNEL_HIGHEST_AMIPMV\", 0);\n        return;\n    }\n    if ($F.getLastHitNumber(\"E_LOAD_PATHRETRIEVE_AMIPMV\") == $H.HitNumber && $F.getLastStepNumber(\"E_LOAD_PATHRETRIEVE_AMIPMV\") == $H.StepNumber)\n    {\n        $F.setFacts(\"E_FUNNEL_HIGHEST_AMIPMV\", 1);\n        return;\n    }\n    \n    var prev = $F.getLastEventNumericValue(\"E_FUNNEL_HIGHEST_AMIPMV\");\n    \n    if ($F.getLastHitNumber(\"E_LOAD_PATH1_AMIPMV\") == $H.HitNumber && $F.getLastStepNumber(\"E_LOAD_PATH1_AMIPMV\") == $H.StepNumber && prev < 1)\n    {\n        $F.setFacts(\"E_FUNNEL_HIGHEST_AMIPMV\", 1);\n        return;\n    }\n    if ($F.getLastHitNumber(\"E_LOAD_PATH2_AMIPMV\") == $H.HitNumber && $F.getLastStepNumber(\"E_LOAD_PATH2_AMIPMV\") == $H.StepNumber && prev < 2)\n    {\n        $F.setFacts(\"E_FUNNEL_HIGHEST_AMIPMV\", 2);\n        return;\n    }\n    if ($F.getLastHitNumber(\"E_LOAD_PATH3_AMIPMV\") == $H.HitNumber && $F.getLastStepNumber(\"E_LOAD_PATH3_AMIPMV\") == $H.StepNumber && prev < 3)\n    {\n        $F.setFacts(\"E_FUNNEL_HIGHEST_AMIPMV\", 3);\n        return;\n    }\n    if ($F.getLastHitNumber(\"E_LOAD_PATH4_AMIPMV\") == $H.HitNumber && $F.getLastStepNumber(\"E_LOAD_PATH4_AMIPMV\") == $H.StepNumber && prev < 4)\n    {\n        $F.setFacts(\"E_FUNNEL_HIGHEST_AMIPMV\", 4);\n        return;\n    }\n    if ($F.getLastHitNumber(\"E_LOAD_PATH5_AMIPMV\") == $H.HitNumber && $F.getLastStepNumber(\"E_LOAD_PATH5_AMIPMV\") == $H.StepNumber && prev < 5)\n    {\n        $F.setFacts(\"E_FUNNEL_HIGHEST_AMIPMV\", 5);\n        return;\n    }\n    if ($F.getLastHitNumber(\"E_LOAD_PATH6_AMIPMV\") == $H.HitNumber && $F.getLastStepNumber(\"E_LOAD_PATH6_AMIPMV\") == $H.StepNumber && prev < 6)\n    {\n        $F.setFacts(\"E_FUNNEL_HIGHEST_AMIPMV\", 6);\n        return;\n    }\n    if ($F.getLastHitNumber(\"E_LOAD_PATH7_AMIPMV\") == $H.HitNumber && $F.getLastStepNumber(\"E_LOAD_PATH7_AMIPMV\") == $H.StepNumber && prev < 7)\n    {\n        $F.setFacts(\"E_FUNNEL_HIGHEST_AMIPMV\", 7);\n        return;\n    }\n    if ($F.getLastHitNumber(\"E_LOAD_PATH8_AMIPMV\") == $H.HitNumber && $F.getLastStepNumber(\"E_LOAD_PATH8_AMIPMV\") == $H.StepNumber && prev < 8)\n    {\n        $F.setFacts(\"E_FUNNEL_HIGHEST_AMIPMV\", 8);\n        return;\n    }\n    if ($F.getLastHitNumber(\"E_LOAD_PATH9_AMIPMV\") == $H.HitNumber && $F.getLastStepNumber(\"E_LOAD_PATH9_AMIPMV\") == $H.StepNumber0 && prev < 9)\n    {\n        $F.setFacts(\"E_FUNNEL_HIGHEST_AMIPMV\", 9);\n        return;\n    }\n}",
      "conditionGroup": {
        "conditionOperator": "Or",
        "distanceOperator": "GreaterThan",
        "conditions": [
          {
            "leftOperand": {
              "displayName": "Load - /path1 [ami/pmv]",
              "internalName": "E_LOAD_PATH1_AMIPMV",
              "type": "Event"
            },
            "leftOperandValueType": "Fact",
            "method": "ExistsOnStep",
            "conditionOperator": "IsTrue",
            "rightOperandValue": "",
            "rightOperandValueType": "TextLiteral",
            "caseSensitive": false
          },
          {
            "leftOperand": {
              "displayName": "Load - /path2 [ami/pmv]",
              "internalName": "E_LOAD_PATH2_AMIPMV",
              "type": "Event"
            },
            "leftOperandValueType": "Fact",
            "method": "ExistsOnStep",
            "conditionOperator": "IsTrue",
            "rightOperandValue": "",
            "rightOperandValueType": "TextLiteral",
            "caseSensitive": false
          },
          {
            "leftOperand": {
              "displayName": "Load - /path3 [ami/pmv]",
              "internalName": "E_LOAD_PATH3_AMIPMV",
              "type": "Event"
            },
            "leftOperandValueType": "Fact",
            "method": "ExistsOnStep",
            "conditionOperator": "IsTrue",
            "rightOperandValue": "",
            "rightOperandValueType": "TextLiteral",
            "caseSensitive": false
          },
          {
            "leftOperand": {
              "displayName": "Load - /path4 [ami/pmv]",
              "internalName": "E_LOAD_PATH4_AMIPMV",
              "type": "Event"
            },
            "leftOperandValueType": "Fact",
            "method": "ExistsOnStep",
            "conditionOperator": "IsTrue",
            "rightOperandValue": "",
            "rightOperandValueType": "TextLiteral",
            "caseSensitive": false
          },
          {
            "leftOperand": {
              "displayName": "Load - /path5 [ami/pmv]",
              "internalName": "E_LOAD_PATH5_AMIPMV",
              "type": "Event"
            },
            "leftOperandValueType": "Fact",
            "method": "ExistsOnStep",
            "conditionOperator": "IsTrue",
            "rightOperandValue": "",
            "rightOperandValueType": "TextLiteral",
            "caseSensitive": false
          },
          {
            "leftOperand": {
              "displayName": "Load - /path6 [ami/pmv]",
              "internalName": "E_LOAD_PATH6_AMIPMV",
              "type": "Event"
            },
            "leftOperandValueType": "Fact",
            "method": "ExistsOnStep",
            "conditionOperator": "IsTrue",
            "rightOperandValue": "",
            "rightOperandValueType": "TextLiteral",
            "caseSensitive": false
          },
          {
            "leftOperand": {
              "displayName": "Load - /path7 [ami/pmv]",
              "internalName": "E_LOAD_PATH7_AMIPMV",
              "type": "Event"
            },
            "leftOperandValueType": "Fact",
            "method": "ExistsOnStep",
            "conditionOperator": "IsTrue",
            "rightOperandValue": "",
            "rightOperandValueType": "TextLiteral",
            "caseSensitive": false
          },
          {
            "leftOperand": {
              "displayName": "Load - /path8 [ami/pmv]",
              "internalName": "E_LOAD_PATH8_AMIPMV",
              "type": "Event"
            },
            "leftOperandValueType": "Fact",
            "method": "ExistsOnStep",
            "conditionOperator": "IsTrue",
            "rightOperandValue": "",
            "rightOperandValueType": "TextLiteral",
            "caseSensitive": false
          },
          {
            "leftOperand": {
              "displayName": "Load - /path9 [ami/pmv]",
              "internalName": "E_LOAD_PATH9_AMIPMV",
              "type": "Event"
            },
            "leftOperandValueType": "Fact",
            "method": "ExistsOnStep",
            "conditionOperator": "IsTrue",
            "rightOperandValue": "",
            "rightOperandValueType": "TextLiteral",
            "caseSensitive": false
          },
          {
            "leftOperand": {
              "displayName": "Load - /pathConfirm [ami/pmv]",
              "internalName": "E_LOAD_PATHCONFIRM_AMIPMV",
              "type": "Event"
            },
            "leftOperandValueType": "Fact",
            "method": "ExistsOnStep",
            "conditionOperator": "IsTrue",
            "rightOperandValue": "",
            "rightOperandValueType": "TextLiteral",
            "caseSensitive": false
          },
          {
            "leftOperand": {
              "displayName": "Load - /pathRetrieve [ami/pmv]",
              "internalName": "E_LOAD_PATHRETRIEVE_AMIPMV",
              "type": "Event"
            },
            "leftOperandValueType": "Fact",
            "method": "ExistsOnStep",
            "conditionOperator": "IsTrue",
            "rightOperandValue": "",
            "rightOperandValueType": "TextLiteral",
            "caseSensitive": false
          }
        ],
        "lowerBound": 0.0,
        "upperBound": 0.0
      },
      "referenceValueType": "Custom",
      "valueType": "Numeric",
      "storeMetrics": "Count",
      "track": "AllOccurrence",
      "forSupportUserOnly": true,
      "buildingBlockOnly": true,
      "discardSession": false,
      "geoAnalyticsEnabled": false,
      "dimensionGroups": {}
    },
    {
      "displayName": "Funnel - /path1 [ami/pmv]",
      "internalName": "E_FUNNEL_PATH1_AMIPMV",
      "capturePersonalData": false,
      "active": true,
      "tags": [
        "funnel [ami/pmv]"
      ],
      "trigger": "EveryStep",
      "publish": "Immediate",
      "mode": "Basic",
      "javascript": "// NOTE: Do not change event name\nfunction E_FUNNEL_PATH1_AMIPMV()\n{\n    if ($F.getLastHitNumber(\"E_LOAD_PATH1_AMIPMV\") == $H.HitNumber && $F.getLastStepNumber(\"E_LOAD_PATH1_AMIPMV\") == $H.StepNumber && $F.getLastEventNumericValue(\"E_FUNNEL_HIGHEST_AMIPMV\") < 1)\n    {\n        $F.setFacts(\"E_FUNNEL_PATH1_AMIPMV\");\n    }\n}",
      "conditionGroup": {
        "conditionOperator": "And",
        "distanceOperator": "GreaterThan",
        "conditions": [
          {
            "leftOperand": {
              "displayName": "Load - /path1 [ami/pmv]",
              "internalName": "E_LOAD_PATH1_AMIPMV",
              "type": "Event"
            },
            "leftOperandValueType": "Fact",
            "method": "ExistsOnStep",
            "conditionOperator": "IsTrue",
            "rightOperandValue": "",
            "rightOperandValueType": "TextLiteral",
            "caseSensitive": false
          },
          {
            "leftOperand": {
              "displayName": "Funnel highest [ami/pmv]",
              "internalName": "E_FUNNEL_HIGHEST_AMIPMV",
              "type": "Event"
            },
            "leftOperandValueType": "Fact",
            "method": "NumericValue",
            "conditionOperator": "LessThan",
            "rightOperandValue": "1",
            "rightOperandValueType": "NumericLiteral",
            "caseSensitive": false
          }
        ],
        "lowerBound": 0.0,
        "upperBound": 0.0
      },
      "referenceValueType": "Custom",
      "valueType": "Text",
      "storeMetrics": "Count",
      "track": "AllOccurrence",
      "forSupportUserOnly": false,
      "buildingBlockOnly": false,
      "discardSession": false,
      "geoAnalyticsEnabled": false,
      "dimensionGroups": {
        "Funnel context": false
      }
    },
    {
      "displayName": "Funnel - /path2 [ami/pmv]",
      "internalName": "E_FUNNEL_PATH2_AMIPMV",
      "capturePersonalData": false,
      "active": true,
      "tags": [
        "funnel [ami/pmv]"
      ],
      "trigger": "EveryStep",
      "publish": "Immediate",
      "mode": "Basic",
      "javascript": "// NOTE: Do not change event name\nfunction E_FUNNEL_PATH2_AMIPMV()\n{\n    if ($F.getLastHitNumber(\"E_LOAD_PATH2_AMIPMV\") == $H.HitNumber && $F.getLastStepNumber(\"E_LOAD_PATH2_AMIPMV\") == $H.StepNumber && $F.getLastEventNumericValue(\"E_FUNNEL_HIGHEST_AMIPMV\") < 2)\n    {\n        $F.setFacts(\"E_FUNNEL_PATH2_AMIPMV\");\n    }\n}",
      "conditionGroup": {
        "conditionOperator": "And",
        "distanceOperator": "GreaterThan",
        "conditions": [
          {
            "leftOperand": {
              "displayName": "Load - /path2 [ami/pmv]",
              "internalName": "E_LOAD_PATH2_AMIPMV",
              "type": "Event"
            },
            "leftOperandValueType": "Fact",
            "method": "ExistsOnStep",
            "conditionOperator": "IsTrue",
            "rightOperandValue": "",
            "rightOperandValueType": "TextLiteral",
            "caseSensitive": false
          },
          {
            "leftOperand": {
              "displayName": "Funnel highest [ami/pmv]",
              "internalName": "E_FUNNEL_HIGHEST_AMIPMV",
              "type": "Event"
            },
            "leftOperandValueType": "Fact",
            "method": "NumericValue",
            "conditionOperator": "LessThan",
            "rightOperandValue": "2",
            "rightOperandValueType": "NumericLiteral",
            "caseSensitive": false
          }
        ],
        "lowerBound": 0.0,
        "upperBound": 0.0
      },
      "referenceValueType": "Custom",
      "valueType": "Text",
      "storeMetrics": "Count",
      "track": "AllOccurrence",
      "forSupportUserOnly": false,
      "buildingBlockOnly": false,
      "discardSession": false,
      "geoAnalyticsEnabled": false,
      "dimensionGroups": {
        "Funnel context": false
      }
    },
    {
      "displayName": "Funnel - /path3 [ami/pmv]",
      "internalName": "E_FUNNEL_PATH3_AMIPMV",
      "capturePersonalData": false,
      "active": true,
      "tags": [
        "funnel [ami/pmv]"
      ],
      "trigger": "EveryStep",
      "publish": "Immediate",
      "mode": "Basic",
      "javascript": "// NOTE: Do not change event name\nfunction E_FUNNEL_PATH3_AMIPMV()\n{\n    if ($F.getLastHitNumber(\"E_LOAD_PATH3_AMIPMV\") == $H.HitNumber && $F.getLastStepNumber(\"E_LOAD_PATH3_AMIPMV\") == $H.StepNumber && $F.getLastEventNumericValue(\"E_FUNNEL_HIGHEST_AMIPMV\") < 3)\n    {\n        $F.setFacts(\"E_FUNNEL_PATH3_AMIPMV\");\n    }\n}",
      "conditionGroup": {
        "conditionOperator": "And",
        "distanceOperator": "GreaterThan",
        "conditions": [
          {
            "leftOperand": {
              "displayName": "Load - /path3 [ami/pmv]",
              "internalName": "E_LOAD_PATH3_AMIPMV",
              "type": "Event"
            },
            "leftOperandValueType": "Fact",
            "method": "ExistsOnStep",
            "conditionOperator": "IsTrue",
            "rightOperandValue": "",
            "rightOperandValueType": "TextLiteral",
            "caseSensitive": false
          },
          {
            "leftOperand": {
              "displayName": "Funnel highest [ami/pmv]",
              "internalName": "E_FUNNEL_HIGHEST_AMIPMV",
              "type": "Event"
            },
            "leftOperandValueType": "Fact",
            "method": "NumericValue",
            "conditionOperator": "LessThan",
            "rightOperandValue": "3",
            "rightOperandValueType": "NumericLiteral",
            "caseSensitive": false
          }
        ],
        "lowerBound": 0.0,
        "upperBound": 0.0
      },
      "referenceValueType": "Custom",
      "valueType": "Text",
      "storeMetrics": "Count",
      "track": "AllOccurrence",
      "forSupportUserOnly": false,
      "buildingBlockOnly": false,
      "discardSession": false,
      "geoAnalyticsEnabled": false,
      "dimensionGroups": {
        "Funnel context": false
      }
    },
    {
      "displayName": "Funnel - /path4 [ami/pmv]",
      "internalName": "E_FUNNEL_PATH4_AMIPMV",
      "capturePersonalData": false,
      "active": true,
      "tags": [
        "funnel [ami/pmv]"
      ],
      "trigger": "EveryStep",
      "publish": "Immediate",
      "mode": "Basic",
      "javascript": "// NOTE: Do not change event name\nfunction E_FUNNEL_PATH4_AMIPMV()\n{\n    if ($F.getLastHitNumber(\"E_LOAD_PATH4_AMIPMV\") == $H.HitNumber && $F.getLastStepNumber(\"E_LOAD_PATH4_AMIPMV\") == $H.StepNumber && $F.getLastEventNumericValue(\"E_FUNNEL_HIGHEST_AMIPMV\") < 4)\n    {\n        $F.setFacts(\"E_FUNNEL_PATH4_AMIPMV\");\n    }\n}",
      "conditionGroup": {
        "conditionOperator": "And",
        "distanceOperator": "GreaterThan",
        "conditions": [
          {
            "leftOperand": {
              "displayName": "Load - /path4 [ami/pmv]",
              "internalName": "E_LOAD_PATH4_AMIPMV",
              "type": "Event"
            },
            "leftOperandValueType": "Fact",
            "method": "ExistsOnStep",
            "conditionOperator": "IsTrue",
            "rightOperandValue": "",
            "rightOperandValueType": "TextLiteral",
            "caseSensitive": false
          },
          {
            "leftOperand": {
              "displayName": "Funnel highest [ami/pmv]",
              "internalName": "E_FUNNEL_HIGHEST_AMIPMV",
              "type": "Event"
            },
            "leftOperandValueType": "Fact",
            "method": "NumericValue",
            "conditionOperator": "LessThan",
            "rightOperandValue": "4",
            "rightOperandValueType": "NumericLiteral",
            "caseSensitive": false
          }
        ],
        "lowerBound": 0.0,
        "upperBound": 0.0
      },
      "referenceValueType": "Custom",
      "valueType": "Text",
      "storeMetrics": "Count",
      "track": "AllOccurrence",
      "forSupportUserOnly": false,
      "buildingBlockOnly": false,
      "discardSession": false,
      "geoAnalyticsEnabled": false,
      "dimensionGroups": {
        "Funnel context": false
      }
    },
    {
      "displayName": "Funnel - /path5 [ami/pmv]",
      "internalName": "E_FUNNEL_PATH5_AMIPMV",
      "capturePersonalData": false,
      "active": true,
      "tags": [
        "funnel [ami/pmv]"
      ],
      "trigger": "EveryStep",
      "publish": "Immediate",
      "mode": "Basic",
      "javascript": "// NOTE: Do not change event name\nfunction E_FUNNEL_PATH5_AMIPMV()\n{\n    if ($F.getLastHitNumber(\"E_LOAD_PATH5_AMIPMV\") == $H.HitNumber && $F.getLastStepNumber(\"E_LOAD_PATH5_AMIPMV\") == $H.StepNumber && $F.getLastEventNumericValue(\"E_FUNNEL_HIGHEST_AMIPMV\") < 5)\n    {\n        $F.setFacts(\"E_FUNNEL_PATH5_AMIPMV\");\n    }\n}",
      "conditionGroup": {
        "conditionOperator": "And",
        "distanceOperator": "GreaterThan",
        "conditions": [
          {
            "leftOperand": {
              "displayName": "Load - /path5 [ami/pmv]",
              "internalName": "E_LOAD_PATH5_AMIPMV",
              "type": "Event"
            },
            "leftOperandValueType": "Fact",
            "method": "ExistsOnStep",
            "conditionOperator": "IsTrue",
            "rightOperandValue": "",
            "rightOperandValueType": "TextLiteral",
            "caseSensitive": false
          },
          {
            "leftOperand": {
              "displayName": "Funnel highest [ami/pmv]",
              "internalName": "E_FUNNEL_HIGHEST_AMIPMV",
              "type": "Event"
            },
            "leftOperandValueType": "Fact",
            "method": "NumericValue",
            "conditionOperator": "LessThan",
            "rightOperandValue": "5",
            "rightOperandValueType": "NumericLiteral",
            "caseSensitive": false
          }
        ],
        "lowerBound": 0.0,
        "upperBound": 0.0
      },
      "referenceValueType": "Custom",
      "valueType": "Text",
      "storeMetrics": "Count",
      "track": "AllOccurrence",
      "forSupportUserOnly": false,
      "buildingBlockOnly": false,
      "discardSession": false,
      "geoAnalyticsEnabled": false,
      "dimensionGroups": {
        "Funnel context": false
      }
    },
    {
      "displayName": "Funnel - /path6 [ami/pmv]",
      "internalName": "E_FUNNEL_PATH6_AMIPMV",
      "capturePersonalData": false,
      "active": true,
      "tags": [
        "funnel [ami/pmv]"
      ],
      "trigger": "EveryStep",
      "publish": "Immediate",
      "mode": "Basic",
      "javascript": "// NOTE: Do not change event name\nfunction E_FUNNEL_PATH6_AMIPMV()\n{\n    if ($F.getLastHitNumber(\"E_LOAD_PATH6_AMIPMV\") == $H.HitNumber && $F.getLastStepNumber(\"E_LOAD_PATH6_AMIPMV\") == $H.StepNumber && $F.getLastEventNumericValue(\"E_FUNNEL_HIGHEST_AMIPMV\") < 6)\n    {\n        $F.setFacts(\"E_FUNNEL_PATH6_AMIPMV\");\n    }\n}",
      "conditionGroup": {
        "conditionOperator": "And",
        "distanceOperator": "GreaterThan",
        "conditions": [
          {
            "leftOperand": {
              "displayName": "Load - /path6 [ami/pmv]",
              "internalName": "E_LOAD_PATH6_AMIPMV",
              "type": "Event"
            },
            "leftOperandValueType": "Fact",
            "method": "ExistsOnStep",
            "conditionOperator": "IsTrue",
            "rightOperandValue": "",
            "rightOperandValueType": "TextLiteral",
            "caseSensitive": false
          },
          {
            "leftOperand": {
              "displayName": "Funnel highest [ami/pmv]",
              "internalName": "E_FUNNEL_HIGHEST_AMIPMV",
              "type": "Event"
            },
            "leftOperandValueType": "Fact",
            "method": "NumericValue",
            "conditionOperator": "LessThan",
            "rightOperandValue": "6",
            "rightOperandValueType": "NumericLiteral",
            "caseSensitive": false
          }
        ],
        "lowerBound": 0.0,
        "upperBound": 0.0
      },
      "referenceValueType": "Custom",
      "valueType": "Text",
      "storeMetrics": "Count",
      "track": "AllOccurrence",
      "forSupportUserOnly": false,
      "buildingBlockOnly": false,
      "discardSession": false,
      "geoAnalyticsEnabled": false,
      "dimensionGroups": {
        "Funnel context": false
      }
    },
    {
      "displayName": "Funnel - /path7 [ami/pmv]",
      "internalName": "E_FUNNEL_PATH7_AMIPMV",
      "capturePersonalData": false,
      "active": true,
      "tags": [
        "funnel [ami/pmv]"
      ],
      "trigger": "EveryStep",
      "publish": "Immediate",
      "mode": "Basic",
      "javascript": "// NOTE: Do not change event name\nfunction E_FUNNEL_PATH7_AMIPMV()\n{\n    if ($F.getLastHitNumber(\"E_LOAD_PATH7_AMIPMV\") == $H.HitNumber && $F.getLastStepNumber(\"E_LOAD_PATH7_AMIPMV\") == $H.StepNumber && $F.getLastEventNumericValue(\"E_FUNNEL_HIGHEST_AMIPMV\") < 7)\n    {\n        $F.setFacts(\"E_FUNNEL_PATH7_AMIPMV\");\n    }\n}",
      "conditionGroup": {
        "conditionOperator": "And",
        "distanceOperator": "GreaterThan",
        "conditions": [
          {
            "leftOperand": {
              "displayName": "Load - /path7 [ami/pmv]",
              "internalName": "E_LOAD_PATH7_AMIPMV",
              "type": "Event"
            },
            "leftOperandValueType": "Fact",
            "method": "ExistsOnStep",
            "conditionOperator": "IsTrue",
            "rightOperandValue": "",
            "rightOperandValueType": "TextLiteral",
            "caseSensitive": false
          },
          {
            "leftOperand": {
              "displayName": "Funnel highest [ami/pmv]",
              "internalName": "E_FUNNEL_HIGHEST_AMIPMV",
              "type": "Event"
            },
            "leftOperandValueType": "Fact",
            "method": "NumericValue",
            "conditionOperator": "LessThan",
            "rightOperandValue": "7",
            "rightOperandValueType": "NumericLiteral",
            "caseSensitive": false
          }
        ],
        "lowerBound": 0.0,
        "upperBound": 0.0
      },
      "referenceValueType": "Custom",
      "valueType": "Text",
      "storeMetrics": "Count",
      "track": "AllOccurrence",
      "forSupportUserOnly": false,
      "buildingBlockOnly": false,
      "discardSession": false,
      "geoAnalyticsEnabled": false,
      "dimensionGroups": {
        "Funnel context": false
      }
    },
    {
      "displayName": "Funnel - /path8 [ami/pmv]",
      "internalName": "E_FUNNEL_PATH8_AMIPMV",
      "capturePersonalData": false,
      "active": true,
      "tags": [
        "funnel [ami/pmv]"
      ],
      "trigger": "EveryStep",
      "publish": "Immediate",
      "mode": "Basic",
      "javascript": "// NOTE: Do not change event name\nfunction E_FUNNEL_PATH8_AMIPMV()\n{\n    if ($F.getLastHitNumber(\"E_LOAD_PATH8_AMIPMV\") == $H.HitNumber && $F.getLastStepNumber(\"E_LOAD_PATH8_AMIPMV\") == $H.StepNumber && $F.getLastEventNumericValue(\"E_FUNNEL_HIGHEST_AMIPMV\") < 8)\n    {\n        $F.setFacts(\"E_FUNNEL_PATH8_AMIPMV\");\n    }\n}",
      "conditionGroup": {
        "conditionOperator": "And",
        "distanceOperator": "GreaterThan",
        "conditions": [
          {
            "leftOperand": {
              "displayName": "Load - /path8 [ami/pmv]",
              "internalName": "E_LOAD_PATH8_AMIPMV",
              "type": "Event"
            },
            "leftOperandValueType": "Fact",
            "method": "ExistsOnStep",
            "conditionOperator": "IsTrue",
            "rightOperandValue": "",
            "rightOperandValueType": "TextLiteral",
            "caseSensitive": false
          },
          {
            "leftOperand": {
              "displayName": "Funnel highest [ami/pmv]",
              "internalName": "E_FUNNEL_HIGHEST_AMIPMV",
              "type": "Event"
            },
            "leftOperandValueType": "Fact",
            "method": "NumericValue",
            "conditionOperator": "LessThan",
            "rightOperandValue": "8",
            "rightOperandValueType": "NumericLiteral",
            "caseSensitive": false
          }
        ],
        "lowerBound": 0.0,
        "upperBound": 0.0
      },
      "referenceValueType": "Custom",
      "valueType": "Text",
      "storeMetrics": "Count",
      "track": "AllOccurrence",
      "forSupportUserOnly": false,
      "buildingBlockOnly": false,
      "discardSession": false,
      "geoAnalyticsEnabled": false,
      "dimensionGroups": {
        "Funnel context": false
      }
    },
    {
      "displayName": "Funnel - /path9 [ami/pmv]",
      "internalName": "E_FUNNEL_PATH9_AMIPMV",
      "capturePersonalData": false,
      "active": true,
      "tags": [
        "funnel [ami/pmv]"
      ],
      "trigger": "EveryStep",
      "publish": "Immediate",
      "mode": "Basic",
      "javascript": "// NOTE: Do not change event name\nfunction E_FUNNEL_PATH9_AMIPMV()\n{\n    if ($F.getLastHitNumber(\"E_LOAD_PATH9_AMIPMV\") == $H.HitNumber && $F.getLastStepNumber(\"E_LOAD_PATH9_AMIPMV\") == $H.StepNumber && $F.getLastEventNumericValue(\"E_FUNNEL_HIGHEST_AMIPMV\") < 9)\n    {\n        $F.setFacts(\"E_FUNNEL_PATH9_AMIPMV\");\n    }\n}",
      "conditionGroup": {
        "conditionOperator": "And",
        "distanceOperator": "GreaterThan",
        "conditions": [
          {
            "leftOperand": {
              "displayName": "Load - /path9 [ami/pmv]",
              "internalName": "E_LOAD_PATH9_AMIPMV",
              "type": "Event"
            },
            "leftOperandValueType": "Fact",
            "method": "ExistsOnStep",
            "conditionOperator": "IsTrue",
            "rightOperandValue": "",
            "rightOperandValueType": "TextLiteral",
            "caseSensitive": false
          },
          {
            "leftOperand": {
              "displayName": "Funnel highest [ami/pmv]",
              "internalName": "E_FUNNEL_HIGHEST_AMIPMV",
              "type": "Event"
            },
            "leftOperandValueType": "Fact",
            "method": "NumericValue",
            "conditionOperator": "LessThan",
            "rightOperandValue": "9",
            "rightOperandValueType": "NumericLiteral",
            "caseSensitive": false
          }
        ],
        "lowerBound": 0.0,
        "upperBound": 0.0
      },
      "referenceValueType": "Custom",
      "valueType": "Text",
      "storeMetrics": "Count",
      "track": "AllOccurrence",
      "forSupportUserOnly": false,
      "buildingBlockOnly": false,
      "discardSession": false,
      "geoAnalyticsEnabled": false,
      "dimensionGroups": {
        "Funnel context": false
      }
    },
    {
      "displayName": "Funnel - /pathConfirm",
      "internalName": "E_FUNNEL_PATHCONFIRM",
      "capturePersonalData": false,
      "active": true,
      "tags": [
        "funnel [ami/pmv]"
      ],
      "trigger": "EveryStep",
      "publish": "Immediate",
      "mode": "Basic",
      "javascript": "// NOTE: Do not change event name\nfunction E_FUNNEL_PATHCONFIRM()\n{\n    if ($F.getLastHitNumber(\"E_LOAD_PATHCONFIRM_AMIPMV\") == $H.HitNumber && $F.getLastStepNumber(\"E_LOAD_PATHCONFIRM_AMIPMV\") == $H.StepNumber)\n    {\n        $F.setFacts(\"E_FUNNEL_PATHCONFIRM\");\n    }\n}",
      "conditionGroup": {
        "conditionOperator": "And",
        "distanceOperator": "GreaterThan",
        "conditions": [
          {
            "leftOperand": {
              "displayName": "Load - /pathConfirm [ami/pmv]",
              "internalName": "E_LOAD_PATHCONFIRM_AMIPMV",
              "type": "Event"
            },
            "leftOperandValueType": "Fact",
            "method": "ExistsOnStep",
            "conditionOperator": "IsTrue",
            "rightOperandValue": "",
            "rightOperandValueType": "TextLiteral",
            "caseSensitive": false
          }
        ],
        "lowerBound": 0.0,
        "upperBound": 0.0
      },
      "referenceValueType": "Custom",
      "valueType": "Text",
      "storeMetrics": "Count",
      "track": "AllOccurrence",
      "forSupportUserOnly": false,
      "buildingBlockOnly": false,
      "discardSession": false,
      "geoAnalyticsEnabled": false,
      "dimensionGroups": {
        "Funnel context": false
      }
    },
    {
      "displayName": "Funnel - /pathRetrieve",
      "internalName": "E_FUNNEL_PATHRETRIEVE",
      "capturePersonalData": false,
      "active": true,
      "tags": [
        "funnel [ami/pmv]"
      ],
      "trigger": "EveryStep",
      "publish": "Immediate",
      "mode": "Basic",
      "javascript": "// NOTE: Do not change event name\nfunction E_FUNNEL_PATHRETRIEVE()\n{\n    if ($F.getLastHitNumber(\"E_LOAD_PATHRETRIEVE_AMIPMV\") == $H.HitNumber && $F.getLastStepNumber(\"E_LOAD_PATHRETRIEVE_AMIPMV\") == $H.StepNumber)\n    {\n        $F.setFacts(\"E_FUNNEL_PATHRETRIEVE\");\n    }\n}",
      "conditionGroup": {
        "conditionOperator": "And",
        "distanceOperator": "GreaterThan",
        "conditions": [
          {
            "leftOperand": {
              "displayName": "Load - /pathRetrieve [ami/pmv]",
              "internalName": "E_LOAD_PATHRETRIEVE_AMIPMV",
              "type": "Event"
            },
            "leftOperandValueType": "Fact",
            "method": "ExistsOnStep",
            "conditionOperator": "IsTrue",
            "rightOperandValue": "",
            "rightOperandValueType": "TextLiteral",
            "caseSensitive": false
          }
        ],
        "lowerBound": 0.0,
        "upperBound": 0.0
      },
      "referenceValueType": "Custom",
      "valueType": "Text",
      "storeMetrics": "Count",
      "track": "AllOccurrence",
      "forSupportUserOnly": false,
      "buildingBlockOnly": false,
      "discardSession": false,
      "geoAnalyticsEnabled": false,
      "dimensionGroups": {
        "Funnel context": false
      }
    }
  ],
  "dimensions": [
    {
      "displayName": "Funnel type",
      "internalName": "DIM_FUNNEL_TYPE",
      "tags": [
        "funnel [ami/pmv]"
      ],
      "active": true,
      "capturePersonalData": false,
      "populatedBy": {
        "displayName": "Funnel type",
        "internalName": "SSV_1170",
        "type": "SessionAttribute"
      },
      "defaultValue": "Unknown",
      "publish": "Immediate",
      "whiteList": [],
      "valueToRecord": "WhiteListPlusObservedValues",
      "maxObservedValues": 1000,
      "turnOnLogging": false
    }
  ],
  "dimensionGroups": [
    {
      "displayName": "Funnel context",
      "internalName": "DG_FUNNEL_CONTEXT",
      "tags": [
        "funnel [ami/pmv]"
      ],
      "active": true,
      "dimensions": [
        "Funnel type"
      ]
    }
  ],
  "sessionAttributes": [
    {
      "displayName": "Funnel type",
      "internalName": "SSV_1170",
      "tags": [
        "funnel [ami/pmv]"
      ],
      "active": true,
      "capturePersonalData": false,
      "populatedBy": [
        {
          "displayName": "Load - /path1 [ami/pmv]",
          "internalName": "E_LOAD_PATH1_AMIPMV",
          "type": "Event"
        }
      ],
      "identityType": "None"
    }
  ],
  "hitAttributes": [],
  "stepAttributes": []
}